MANIFEST.in
setup.py
Flask_Twip.egg-info/PKG-INFO
Flask_Twip.egg-info/SOURCES.txt
Flask_Twip.egg-info/dependency_links.txt
Flask_Twip.egg-info/not-zip-safe
Flask_Twip.egg-info/requires.txt
Flask_Twip.egg-info/top_level.txt
flask_twip/__init__.py
flask_twip/backend.py
flask_twip/environment.py
flask_twip/exception.py
flask_twip/twip.py
flask_twip/static/twip.css
flask_twip/templates/base.jinja
flask_twip/templates/show_api.jinja