Metadata-Version: 1.1
Name: Flask-Twip
Version: 0.0.3
Summary: twitter API proxy extension for Flask microframework
Home-page: https://github.com/yegle/flask_twip/
Author: yegle
Author-email: flask_twip.python@yegle.net
License: MPL
Platform: a
Platform: n
Platform: y
Classifier: Environment :: Web Environment
Classifier: Intended Audience :: Developers
Classifier: License :: OSI Approved :: Mozilla Public License 1.1 (MPL 1.1)
Classifier: Operating System :: OS Independent
Classifier: Programming Language :: Python
Classifier: Topic :: Internet :: WWW/HTTP :: Dynamic Content
Classifier: Topic :: Software Development :: Libraries :: Python Modules
